src/__init__.py
src/plugin.py
mkdocs_plugin_inline_ext_svg-0.1.2.dist-info/LICENSE.md
mkdocs_plugin_inline_ext_svg-0.1.2.dist-info/METADATA
mkdocs_plugin_inline_ext_svg-0.1.2.dist-info/WHEEL
mkdocs_plugin_inline_ext_svg-0.1.2.dist-info/entry_points.txt
mkdocs_plugin_inline_ext_svg-0.1.2.dist-info/top_level.txt
mkdocs_plugin_inline_ext_svg-0.1.2.dist-info/RECORD
