Metadata-Version: 2.1
Name: mkdocs-plugin-inline-ext-svg
Version: 0.1.2
Summary: Mkdocs plugin to render inline svg files
Home-page: https://gitlab.com/craig0990/mkdocs-plugin-inline-svg
Author: Craig Roberts
Author-email: Nicolas Dupont <nicolas.dupont@jalios.com>
License: MIT
Keywords: mkdocs plugin inline svg
Classifier: Programming Language :: Python :: 3
Classifier: Operating System :: OS Independent
Requires-Python: >=3.5
License-File: LICENSE.md
Requires-Dist: mkdocs
